migrationTool/CLI.py
migrationTool/__init__.py
migrationTool/__main__.py
migrationTool/gitMigration/Downloader.py
migrationTool/gitMigration/Git.py
migrationTool/gitMigration/GithubUploader.py
migrationTool/gitMigration/GitlabDownloader.py
migrationTool/gitMigration/Uploader.py
migrationTool/gitMigration/__init__.py
migrationTool/gitMigration/largeFiles.py
migrationTool/gitMigration/mavenSecrets.py
migrationTool/gitMigration/repoCleaning.py
migrationTool/migration_types/Architecture.py
migrationTool/migration_types/Config.py
migrationTool/migration_types/Repo.py
migrationTool/migration_types/__init__.py
migrationTool/pipelineMigration/Converter.py
migrationTool/pipelineMigration/DockerMigration.py
migrationTool/pipelineMigration/GithubConverter.py
migrationTool/pipelineMigration/GithubSubtreeConverter.py
migrationTool/pipelineMigration/GitlabCIImporter.py
migrationTool/pipelineMigration/Importer.py
migrationTool/pipelineMigration/Job.py
migrationTool/pipelineMigration/Migration.py
migrationTool/pipelineMigration/Pipeline.py
migrationTool/pipelineMigration/__init__.py
migrationtool_embeddedmontiarc-0.1.0.dist-info/METADATA
migrationtool_embeddedmontiarc-0.1.0.dist-info/WHEEL
migrationtool_embeddedmontiarc-0.1.0.dist-info/entry_points.txt
migrationtool_embeddedmontiarc-0.1.0.dist-info/RECORD
