Metadata-Version: 2.4
Name: migrationTool-EmbeddedMontiArc
Version: 0.1.0
Summary: A CLI tool to migrate git repos from GitLab to GitHub. For this CI/CD pipelines are converted to GitHub Actions.
Author-email: David Blum <david.blum@rwth-aachen.de>
Requires-Python: >=3.7
Requires-Dist: git-filter-repo
Requires-Dist: gitpython~=3.1.44
Requires-Dist: pygithub~=2.6.1
Requires-Dist: python-gitlab~=5.6.0
Requires-Dist: pyyaml~=6.0.2
Requires-Dist: requests~=2.32.3
Requires-Dist: rich~=14.0.0
Requires-Dist: tqdm~=4.67.1
Requires-Dist: typer~=0.15.4
